exectimeit/__init__.py
exectimeit/timeit.py
exectimeit-0.1.3.dist-info/licenses/LICENSE
exectimeit-0.1.3.dist-info/METADATA
exectimeit-0.1.3.dist-info/WHEEL
exectimeit-0.1.3.dist-info/top_level.txt
exectimeit-0.1.3.dist-info/RECORD
